bizerror/__init__.py
bizerror/base.py
bizerror/general.py
bizerror/generator.py
bizerror/tests.py
bizerror-0.4.13.dist-info/licenses/LICENSE
bizerror-0.4.13.dist-info/METADATA
bizerror-0.4.13.dist-info/WHEEL
bizerror-0.4.13.dist-info/entry_points.txt
bizerror-0.4.13.dist-info/top_level.txt
bizerror-0.4.13.dist-info/RECORD
